README.md
setup.py
Askpyro.egg-info/PKG-INFO
Askpyro.egg-info/SOURCES.txt
Askpyro.egg-info/dependency_links.txt
Askpyro.egg-info/not-zip-safe
Askpyro.egg-info/top_level.txt
askpyro/__init__.py
askpyro/conversation.py
askpyro/errors.py
askpyro/helpers/__init__.py
askpyro/helpers/helpers.py
askpyro/helpers/http_helper.py
askpyro/helpers/lock.py
askpyro/helpers/parser.py
askpyro/helpers/pyro_progress.py
askpyro/patch/__init__.py
askpyro/patch/bound/__init__.py
askpyro/patch/bound/message.py
askpyro/patch/methods/__init__.py
askpyro/patch/methods/edit_message_text.py
askpyro/patch/methods/send_as_file.py
askpyro/patch/methods/send_message.py
examples/__init__.py
examples/buttons.py
examples/callback.py
examples/captcha.py
examples/filters.py
examples/start.py