Metadata-Version: 2.1
Name: Askpyro
Version: 1.73.5
Summary: Easy conversation handler for pyrogram
Home-page: https://github.com/Abishnoi69
Author: Abishnoi
Author-email: abishnoi@askpyro.org
License: LGPLv3
Download-URL: https://github.com/Abishnoi69/Askpyro/releases/latest
Project-URL: Tracker, https://github.com/Abishnoi69/Askpyro/issues
Project-URL: Community, https://t.me/AbishnoiMF
Project-URL: Source, https://github.com/Abishnoi69/Askpyro
Project-URL: Documentation, https://github.com/Abishnoi69/askpyro/wiki
Keywords: telegram chat messenger mtproto api client library python conversation
Platform: UNKNOWN
Classifier: Development Status :: 5 - Production/Stable
Classifier: Intended Audience :: Developers
Classifier: Natural Language :: English
Classifier: License :: OSI Approved :: GNU Lesser General Public License v3 (LGPLv3)
Classifier: Operating System :: OS Independent
Classifier: Programming Language :: Python
Classifier: Programming Language :: Python :: 3
Classifier: Programming Language :: Python :: 3.7
Classifier: Programming Language :: Python :: 3.8
Classifier: Programming Language :: Python :: 3.9
Classifier: Programming Language :: Python :: 3.10
Classifier: Programming Language :: Python :: 3.11
Classifier: Programming Language :: Python :: Implementation
Classifier: Programming Language :: Python :: Implementation :: CPython
Classifier: Programming Language :: Python :: Implementation :: PyPy
Classifier: Topic :: Internet
Classifier: Topic :: Communications
Classifier: Topic :: Communications :: Chat
Classifier: Topic :: Software Development :: Libraries
Classifier: Topic :: Software Development :: Libraries :: Python Modules
Classifier: Topic :: Software Development :: Libraries :: Application Frameworks
Requires-Python: ~=3.7
